discord_webhook_decorator/__init__.py
discord_webhook_decorator/decorator.py
automationutils-0.1.0.dist-info/METADATA
automationutils-0.1.0.dist-info/WHEEL
automationutils-0.1.0.dist-info/top_level.txt
automationutils-0.1.0.dist-info/RECORD
