Metadata-Version: 2.1
Name: automationutils
Version: 0.1.0
Summary: A decorator for sending payloads to Discord webhooks
Home-page: https://github.com/lukesudom/automationutils
Author: lukesud0m
Author-email: lukemarshall511@gmail.com
Classifier: Development Status :: 3 - Alpha
Classifier: Intended Audience :: Developers
Classifier: License :: OSI Approved :: MIT License
Classifier: Operating System :: OS Independent
Classifier: Programming Language :: Python :: 3
Classifier: Programming Language :: Python :: 3.6
Classifier: Programming Language :: Python :: 3.7
Classifier: Programming Language :: Python :: 3.8
Classifier: Programming Language :: Python :: 3.9
Requires-Python: >=3.6
Requires-Dist: requests
